setup.cfg
setup.py
pnmatcher/__init__.py
pnmatcher.egg-info/PKG-INFO
pnmatcher.egg-info/SOURCES.txt
pnmatcher.egg-info/dependency_links.txt
pnmatcher.egg-info/requires.txt
pnmatcher.egg-info/top_level.txt
pnmatcher/core/__init__.py
pnmatcher/core/cleaner/__init__.py
pnmatcher/core/common/__init__.py
pnmatcher/core/common/datetime/__init__.py
pnmatcher/core/extractor/__init__.py
pnmatcher/core/normalizer/__init__.py
pnmatcher/core/preprocessor/__init__.py
pnmatcher/core/tokenizer/__init__.py
pnmatcher/core/validator/__init__.py
pnmatcher/res/__init__.py
pnmatcher/res/area_code/__init__.py
pnmatcher/vendor/__init__.py
pnmatcher/vendor/test.py
pnmatcher/vendor/crf/__init__.py
pnmatcher/vendor/crf/crf_tokenizer.py