Metadata-Version: 1.1
Name: pnmatcher
Version: 0.1.2
Summary: match phone numbers in url and text
Home-page: https://github.com/ZwEin27/phone-number-matcher
Author: Lingzhe Teng
Author-email: zwein27@gmail.com
License: UNKNOWN
Download-URL: https://github.com/ZwEin27/phone-number-matcher/tarball/0.1.2
Keywords: phone_number,extractor
Platform: UNKNOWN
